batio/__init__.py
batio/ansi_escapes.py
batio/events.py
batio/linux_terminal.py
batio/vt100_terminal.py
batio/windows_terminal.py
batio-0.2.0.dist-info/LICENSE
batio-0.2.0.dist-info/METADATA
batio-0.2.0.dist-info/WHEEL
batio-0.2.0.dist-info/top_level.txt
batio-0.2.0.dist-info/RECORD
