Metadata-Version: 2.1
Name: batio
Version: 0.2.0
Summary: badass terminal io
Author-email: salt-die <salt-die@protonmail.com>
License: MIT
Project-URL: repository, https://github.com/salt-die/batio
Classifier: Programming Language :: Python :: 3
Classifier: License :: OSI Approved :: MIT License
Classifier: Operating System :: OS Independent
Requires-Python: >=3.12
License-File: LICENSE
